[{"codeforces_contest_id":1670,"codeforces_contest_name":"Codeforces Round #TBA (Div. 2)","codeforces_contest_start_time":"06\/05\/2022 20:05","codeforces_contest_duration":"2 hrs","codeforces_contest_type":"CF"},{"codeforces_contest_id":1662,"codeforces_contest_name":"SWERC 2021-2022 - Online Mirror (Unrated, ICPC Rules, Teams Preferred)","codeforces_contest_start_time":"24\/04\/2022 16:35","codeforces_contest_duration":"5 hrs","codeforces_contest_type":"ICPC"},{"codeforces_contest_id":1672,"codeforces_contest_name":"Codeforces Global Round 20","codeforces_contest_start_time":"23\/04\/2022 19:35","codeforces_contest_duration":"3 hrs","codeforces_contest_type":"CF"},{"codeforces_contest_id":1671,"codeforces_contest_name":"Educational Codeforces Round 127 (Rated for Div. 2)","codeforces_contest_start_time":"22\/04\/2022 20:05","codeforces_contest_duration":"2 hrs","codeforces_contest_type":"ICPC"},{"codeforces_contest_id":1669,"codeforces_contest_name":"Codeforces Round #784 (Div. 4)","codeforces_contest_start_time":"21\/04\/2022 20:05","codeforces_contest_duration":"2 hrs","codeforces_contest_type":"ICPC"},{"codeforces_contest_id":1667,"codeforces_contest_name":"Codeforces Round #783 (Div. 1)","codeforces_contest_start_time":"19\/04\/2022 21:48","codeforces_contest_duration":"2 hrs","codeforces_contest_type":"CF"},{"codeforces_contest_id":1668,"codeforces_contest_name":"Codeforces Round #783 (Div. 2)","codeforces_contest_start_time":"19\/04\/2022 21:48","codeforces_contest_duration":"2 hrs","codeforces_contest_type":"CF"}]